pduino.py
pduino-1.0.0b1.dist-info/METADATA
pduino-1.0.0b1.dist-info/WHEEL
pduino-1.0.0b1.dist-info/top_level.txt
pduino-1.0.0b1.dist-info/RECORD
